fenestrate/__init__.py
fenestrate/fenestrate.py
fenestrate/selectors.py
fenestrate-0.3.0.dist-info/LICENSE
fenestrate-0.3.0.dist-info/WHEEL
fenestrate-0.3.0.dist-info/METADATA
fenestrate-0.3.0.dist-info/RECORD
