Metadata-Version: 2.1
Name: fenestrate
Version: 0.3.0
Summary: 
Author: Vic Putz
Author-email: vbputz@gmail.com
Requires-Python: >=3.9,<4.0
Classifier: Programming Language :: Python :: 3
Classifier: Programming Language :: Python :: 3.9
Requires-Dist: arrow (>=1.1.0,<2.0.0)
Requires-Dist: attrs (>=21.2.0,<22.0.0)
Requires-Dist: icontract (>=2.5.2,<3.0.0)
Requires-Dist: intervaltree (>=3.1.0,<4.0.0)
Requires-Dist: toolz (>=0.11.1,<0.12.0)
